[
    {
        "url": "https://www.sephora.com/ca/en/product/vanilla-royale-sugared-patchouli-%7C-64-eau-de-parfum-intense-travel-spray-P502088",
        "error": "",
        "scrape_timestamp": "08/21/2023, 23:17:31",
        "product_name": "Vanilla Royale Sugared Patchouli | 64 Eau de Parfum Intense Travel Spray",
        "brand_name": "KAYALI",
        "options": [
            {
                "swatch_group": "Mini size",
                "flag_label": null,
                "size": null,
                "name": [
                    "Size: .34 oz / 10 mL"
                ],
                "price": [
                    "$33.00"
                ],
                "sku": "Item 2599959"
            }
        ],
        "rating": "width:68%",
        "product_reviews": "80",
        "ingredients": "Sd Alcohol 40-B/Alcohol Denat., Fragrance/Parfum, Water/Aqua/Eau, Ethylhexyl Methoxycinnamate, Ethylhexyl Salicylate, Butyl Methoxydibenzoylmethane, Cinnamyl Alcohol, Citronellol, Coumarin, Eugenol, Geraniol, Isoeugenol, Limonene, Linalool.",
        "n_loves": "21.7K",
        "categories": [
            "Fragrance",
            "Women",
            "Perfume"
        ]
    },
    {
        "url": "https://www.sephora.com/ca/en/product/kayali-by-huda-yum-pistachio-gelato-33-edp-intense-travel-spray-P506233",
        "error": "",
        "scrape_timestamp": "08/21/2023, 23:17:42",
        "product_name": "YUM PISTACHIO GELATO 33 EDP INTENSE Travel Spray",
        "brand_name": "KAYALI",
        "options": [
            {
                "swatch_group": "Mini size",
                "flag_label": "OUT OF STOCK",
                "size": null,
                "name": [
                    "Size: 0.33 oz / 10 mL eau de parfum spray",
                    "OUT OF STOCK"
                ],
                "price": [
                    "$33.00"
                ],
                "sku": "Item 2634657"
            }
        ],
        "rating": "width:82.026%",
        "product_reviews": "2K",
        "ingredients": "Sd Alcohol 40-B/Alcohol Denat., Fragrance/Parfum, Water/Aqua/Eau, Limonene, Coumarin, Butyl Methoxydibenzoylmethane, Alcohol, Tris(Tetramethylhydroxypiperidinol) Citrate, Alpha-Isomethyl Ionone, Cinnamyl Alcohol, Linalool, Benzyl Alcohol, Benzyl Benzoate, Citral, Citronellol, Farnesol, Geraniol, Hydroxycitronellal, Blue 1/ Ci 42090.",
        "n_loves": "25.8K",
        "categories": [
            "Fragrance",
            "Women",
            "Rollerballs & Travel Size"
        ]
    },
    {
        "url": "https://www.sephora.com/ca/en/product/kayali-by-huda-yum-pistachio-gelato-33-edp-intense-P505421",
        "error": "",
        "scrape_timestamp": "08/21/2023, 23:17:54",
        "product_name": "YUM PISTACHIO GELATO 33 EDP INTENSE",
        "brand_name": "KAYALI",
        "options": [
            {
                "swatch_group": "Standard size",
                "flag_label": null,
                "size": null,
                "name": [
                    "Size: 1.7 oz / 50 mL eau de parfum spray"
                ],
                "price": [
                    "$132.00"
                ],
                "sku": "Item 2634665"
            },
            {
                "swatch_group": "Standard size",
                "flag_label": null,
                "size": null,
                "name": [
                    "Size: 3.4 oz / 100 mL eau de parfum spray"
                ],
                "price": [
                    "$183.00"
                ],
                "sku": "Item 2634673"
            },
            {
                "swatch_group": "Mini size",
                "flag_label": "OUT OF STOCK",
                "size": null,
                "name": [
                    "Size: 0.33 oz / 10 mL eau de parfum spray",
                    "OUT OF STOCK"
                ],
                "price": [
                    "$33.00"
                ],
                "sku": "Item 2634657"
            }
        ],
        "rating": "width:82.026%",
        "product_reviews": "2K",
        "ingredients": "Sd Alcohol 40-B/Alcohol Denat., Fragrance/Parfum, Water/Aqua/Eau, Limonene, Coumarin, Butyl Methoxydibenzoylmethane, Alcohol, Tris(Tetramethylhydroxypiperidinol) Citrate, Alpha-Isomethyl Ionone, Cinnamyl Alcohol, Linalool, Benzyl Alcohol, Benzyl Benzoate, Citral, Citronellol, Farnesol, Geraniol, Hydroxycitronellal, Blue 1/ Ci 42090.",
        "n_loves": "67.3K",
        "categories": [
            "Fragrance",
            "Women",
            "Perfume"
        ]
    },
    {
        "url": "https://www.sephora.com/ca/en/product/huda-beauty-kayali-sweet-diamond-pink-pepper-25-P468826",
        "error": "",
        "scrape_timestamp": "08/21/2023, 23:18:08",
        "product_name": "SWEET DIAMOND PINK PEPPER  | 25",
        "brand_name": "KAYALI",
        "options": [
            {
                "swatch_group": "Standard size",
                "flag_label": null,
                "size": null,
                "name": [
                    "Size: 1.7 oz/ 50 mL Eau De Parfum Intense Spray"
                ],
                "price": [
                    "$135.00"
                ],
                "sku": "Item 2411270"
            },
            {
                "swatch_group": "Standard size",
                "flag_label": null,
                "size": null,
                "name": [
                    "Size: 3.4 oz/ 100 mL Eau de Parfum Intense Spray"
                ],
                "price": [
                    "$185.00"
                ],
                "sku": "Item 2441004"
            },
            {
                "swatch_group": "Mini size",
                "flag_label": null,
                "size": null,
                "name": [
                    "Size: 0.33 oz/ 10 mL"
                ],
                "price": [
                    "$36.00"
                ],
                "sku": "Item 2411288"
            },
            {
                "swatch_group": "Mini size",
                "flag_label": null,
                "size": null,
                "name": [
                    "Size: .34 oz / 10 mL eau de parfum intense spray"
                ],
                "price": [
                    "$33.00"
                ],
                "sku": "Item 2599884"
            }
        ],
        "rating": "width:77.236%",
        "product_reviews": "152",
        "ingredients": "Alcohol Denat./Sd Alcohol 40-B, Fragrance/Parfum, Water/Aqua/Eau, Avobenzone/Butyl Methoxydibenzoylmethane, Alcohol, Tris (Tetramethylhydroxypiperidinol) Citrate, Citral, Citronellol, Eugenol, Geraniol, Isoeugenol, Limonene, Linalool, Benzyl Salicylate, Ext. Violet 2/Ci 60730, Red 4/Ci 14700, Yellow 5/Ci 19140.",
        "n_loves": "24K",
        "categories": [
            "Fragrance",
            "Women",
            "Perfume"
        ]
    },
    {
        "url": "https://www.sephora.com/ca/en/product/huda-beauty-kayali-invite-only-amber-23-deja-vu-white-flower-57-double-rollerball-P476689",
        "error": "",
        "scrape_timestamp": "08/21/2023, 23:18:22",
        "product_name": "INVITE ONLY AMBER | 23 & D\u00c9J\u00c0 VU WHITE FLOWER | 57 Double Rollerball",
        "brand_name": "KAYALI",
        "options": [
            {
                "swatch_group": "Standard size",
                "flag_label": "LIMITED EDITION",
                "size": null,
                "name": [
                    "Size: 2 x 5 mL",
                    "LIMITED EDITION"
                ],
                "price": [
                    "$36.00"
                ],
                "sku": "Item 2476307"
            }
        ],
        "rating": "width:83.334%",
        "product_reviews": "18",
        "ingredients": "Invite Only Amber | 23 Eau De Parfum Intense: Alcohol Denat./Sd Alcohol 40-B, Fragrance/Parfum, Water/Aqua/Eau, Avobenzone/Butyl Methoxydibenzoylmethane, Alcohol, Tris (Tetramethylhydroxypiperidinol) Citrate, Alpha-Isomethyl Ionone, Benzyl Benzoate, Cinnamal, Cinnamyl Alcohol, Coumarin, Linalool, Citral, Citronellol, Eugenol, Farnesol, Geraniol, Limonene, Benzyl Alcohol, Red 4/Ci 14700, Blue 1/Ci 42090, Ext. Violet 2/Ci 60730.D\u00e9j\u00e0 Vu White Flower | 57 Eau De Parfum: Sd Alcohol 40-B/Alcohol Denat., Fragrance/Parfum, Water/Aqua/Eau, Avobenzone/Butyl Methoxydibenzoylmethane, Alcohol, Tris(Tetramethylhydroxypiperidinol) Citrate, Yellow 5/Ci 19140, Ext. Violet 2/Ci 60730, Red 4/Ci 14700, Citral, Citronellol, Eugenol, Farnesol, Geraniol, Hydroxycitronellal, Isoeugenol, Limonene, Linalool, Benzyl Alcohol, Benzyl Benzoate.",
        "n_loves": "7.7K",
        "categories": [
            "Fragrance",
            "Women",
            "Rollerballs & Travel Size"
        ]
    },
    {
        "url": "https://www.sephora.com/ca/en/product/huda-beauty-kayali-vanilla-%7C-28-travel-spray-P468450",
        "error": "",
        "scrape_timestamp": "08/21/2023, 23:18:33",
        "product_name": "VANILLA | 28 Travel Spray",
        "brand_name": "KAYALI",
        "options": [
            {
                "swatch_group": "Mini size",
                "flag_label": null,
                "size": null,
                "name": [
                    "Size: .34 oz / 10 mL eau de parfum spray"
                ],
                "price": [
                    "$33.00"
                ],
                "sku": "Item 2599900"
            }
        ],
        "rating": "width:77.40400000000001%",
        "product_reviews": "1.1K",
        "ingredients": "Sd Alcohol 40-B/Alcohol Denat., Fragrance/Parfum, Water / Aqua / Eau, Butyl Methoxydibenzoylmethane, Alcohol, Tris(Tetramethylhydroxypiperidinol) Citrate, Ci 19140 (Yellow 5), Ci 60730 (Violet 2), Ci 14700 (Red 4), Citronellol, Coumarin, Limonene, Benzyl Salicylate",
        "n_loves": "99.1K",
        "categories": [
            "Fragrance",
            "Women",
            "Rollerballs & Travel Size"
        ]
    },
    {
        "url": "https://www.sephora.com/ca/en/product/kayali-very-sweet-set-P501301",
        "error": "",
        "scrape_timestamp": "08/21/2023, 23:18:45",
        "product_name": "Kayali Very Sweet Set",
        "brand_name": "KAYALI",
        "options": [],
        "rating": "width:62.666%",
        "product_reviews": "30",
        "ingredients": "Vanilla | 28 Eau de Parfum:Sd Alcohol 40-B/Alcohol Denat., Fragrance/Parfum, Water/Aqua/Eau, Butyl Methoxydibenzoylmethane, Alcohol, Tris(Tetramethylhydroxypiperidinol) Citrate, Citronellol, Coumarin, Limonene, Benzyl Salicylate, Ci 14700 (Red 4), Ci 19140 (Yellow 5), Ci 60730 (Ext. Violet 2).HUDA BEAUTY\u2019s Liquid Matte Lipstick:Isododecane, Cyclopentasiloxane, Synthetic Beeswax, Trimethylsiloxysilicate, Polypropylsilsesquioxane, Octyldodecanol, Disteardimonium Hectorite, Mica, Alcohol, Ethyl Vanillin, Propylene Carbonate, Caprylyl Glycol, Flavor/Aroma, Glycerin, Caprylhydroxamic Acid, Water/Aqua/Eau, Phospholipids, Coffea Arabica (Coffee) Seed Extract, Olea Europaea (Olive) Fruit Oil, Ascorbyl Palmitate, Linoleic Acid, Retinyl Palmitate, Tocopheryl Acetate, Lycopene. May Contain (+/-) Iron Oxides (Ci 77491, Ci 77492, Ci 77499), Titanium Dioxide (Ci 77891), Yellow 5 Lake (Ci 19140), Red 6 (Ci 15850), Red 6 Lake (Ci 15850), Red 7 Lake (Ci 15850), Red 28 Lake (Ci 45410), Blue 1 Lake (Ci 42090).",
        "n_loves": "15.7K",
        "categories": [
            "Fragrance",
            "Value & Gift Sets",
            "Perfume Gift Sets"
        ]
    },
    {
        "url": "https://www.sephora.com/ca/en/product/huda-beauty-kayali-elixir-%7C-11-travel-spray-P468447",
        "error": "Product not available",
        "scrape_timestamp": "08/21/2023, 23:18:58"
    },
    {
        "url": "https://www.sephora.com/ca/en/product/huda-beauty-kayali-utopia-vanilla-coco-|-21-P473710",
        "error": "",
        "scrape_timestamp": "08/21/2023, 23:19:07",
        "product_name": "UTOPIA VANILLA COCO | 21",
        "brand_name": "KAYALI",
        "options": [
            {
                "swatch_group": "Standard size",
                "flag_label": null,
                "size": null,
                "name": [
                    "Size: 1.7 oz/ 50 mL Eau de Parfum Intense"
                ],
                "price": [
                    "$135.00"
                ],
                "sku": "Item 2441020"
            },
            {
                "swatch_group": "Standard size",
                "flag_label": null,
                "size": null,
                "name": [
                    "Size: 3.4 oz/ 100 mL Eau de Parfum Intense"
                ],
                "price": [
                    "$185.00"
                ],
                "sku": "Item 2455889"
            },
            {
                "swatch_group": "Mini size",
                "flag_label": null,
                "size": null,
                "name": [
                    "Size: .34 oz / 10 mL"
                ],
                "price": [
                    "$33.00"
                ],
                "sku": "Item 2599892"
            }
        ],
        "rating": "width:73.044%",
        "product_reviews": "161",
        "ingredients": "SD Alcohol 40-B/Alcohol Denat., Fragrance/Parfum, Water/Aqua/Eau, Ethylhexyl Methoxycinnamate, Ethylhexyl Salicylate, Avobenzone/Butyl Methoxydibenzoylmethane, BHT, Citral, Geraniol, Limonene, Linalool, Benzyl Alcohol, Benzyl Salicylate.",
        "n_loves": "41.3K",
        "categories": [
            "Fragrance",
            "Women",
            "Perfume"
        ]
    },
    {
        "url": "https://www.sephora.com/ca/en/product/the-wedding-velvet-santal-35-P506530",
        "error": "",
        "scrape_timestamp": "08/21/2023, 23:19:20",
        "product_name": "The Wedding Velvet Santal 35",
        "brand_name": "KAYALI",
        "options": [
            {
                "swatch_group": "Standard size",
                "flag_label": "NEW",
                "size": null,
                "name": [
                    "Size: 1.7 oz / 50 ml eau de parfum spray",
                    "NEW",
                    "LIMITED EDITION"
                ],
                "price": [
                    "$139.00"
                ],
                "sku": "Item 2705333"
            }
        ],
        "rating": "width:83.334%",
        "product_reviews": "12",
        "ingredients": "Sd Alcohol 40-B/Alcohol Denat., Fragrance/Parfum, Water/Aqua/Eau, Coumarin, Farnesol, Benzyl Benzoate.",
        "n_loves": "4.2K",
        "categories": [
            "Fragrance",
            "Women",
            "Perfume"
        ]
    },
    {
        "url": "https://www.sephora.com/ca/en/product/huda-beauty-kayali-utopia-vanilla-coco-%7C-21-travel-spray-P474954",
        "error": "",
        "scrape_timestamp": "08/21/2023, 23:19:32",
        "product_name": "UTOPIA VANILLA COCO | 21 Travel Spray",
        "brand_name": "KAYALI",
        "options": [
            {
                "swatch_group": "Mini size",
                "flag_label": null,
                "size": null,
                "name": [
                    "Size: .34 oz / 10 mL"
                ],
                "price": [
                    "$33.00"
                ],
                "sku": "Item 2599892"
            }
        ],
        "rating": "width:73.67%",
        "product_reviews": "79",
        "ingredients": "SD Alcohol 40-B/Alcohol Denat., Fragrance/Parfum, Water/Aqua/Eau, Ethylhexyl Methoxycinnamate, Ethylhexyl Salicylate, Avobenzone/Butyl Methoxydibenzoylmethane, BHT, Citral, Geraniol, Limonene, Linalool, Benzyl Alcohol, Benzyl Salicylate.",
        "n_loves": "36.1K",
        "categories": [
            "Fragrance",
            "Women",
            "Rollerballs & Travel Size"
        ]
    },
    {
        "url": "https://www.sephora.com/ca/en/product/huda-beauty-kayali-sweet-diamond-25-utopia-vanilla-coco-21-double-rollerball-P478278",
        "error": "",
        "scrape_timestamp": "08/21/2023, 23:19:45",
        "product_name": "SWEET DIAMOND | 25 & UTOPIA VANILLA COCO | 21 Double Rollerball ",
        "brand_name": "KAYALI",
        "options": [
            {
                "swatch_group": "Standard size",
                "flag_label": null,
                "size": null,
                "name": [
                    "Size: 2 x 5 mL"
                ],
                "price": [
                    "$36.00"
                ],
                "sku": "Item 2441145"
            }
        ],
        "rating": "width:73.334%",
        "product_reviews": "21",
        "ingredients": "Sweet Diamond Pink Pepper | 25 Eau De Parfum: Alcohol Denat./ Sd Alcohol 40-B, Fragrance/Parfum, Water/Aqua/Eau, Avobenzone/Butyl Methoxydibenzoylmethane, Alcohol, Tris (Tetramethylhydroxypiperidinol) Citrate, Citral, Citronellol, Eugenol, Geraniol, Isoeugenol, Limonene, Linalool, Benzyl Salicylate, Ext. Violet 2 / Ci 60730, Red 4 / Ci 14700, Yellow 5 / Ci 19140.Utopia Vanilla Coco | 21 Eau De Parfum: Sd Alcohol 40-B/Alcohol Denat., Fragrance/Parfum, Water/Aqua/Eau, Ethylhexyl Methoxycinnamate, Ethylhexyl Salicylate, Avobenzone/Butyl Methoxydibenzoylmethane, Bht, Citral, Geraniol, Limonene, Linalool, Benzyl Alcohol, Benzyl Salicylate.",
        "n_loves": "14.7K",
        "categories": [
            "Fragrance",
            "Women",
            "Rollerballs & Travel Size"
        ]
    },
    {
        "url": "https://www.sephora.com/ca/en/product/huda-beauty-kayali-vanilla-28-hand-cream-P479485",
        "error": "",
        "scrape_timestamp": "08/21/2023, 23:19:57",
        "product_name": "KAYALI VANILLA | 28 HAND CREAM",
        "brand_name": "KAYALI",
        "options": [
            {
                "swatch_group": "Standard size",
                "flag_label": null,
                "size": null,
                "name": [
                    "Size: 1 oz/ 30 mL"
                ],
                "price": [
                    "$20.00"
                ],
                "sku": "Item 2527281"
            }
        ],
        "rating": "width:71.112%",
        "product_reviews": "9",
        "ingredients": "Water/Aqua/Eau, Fragrance/Parfum, Stearyl Alcohol, Caprylic/Capric Triglyceride, Carthamus Tinctorius (Safflower) Seed Oil, Polyglyceryl-2 Stearate, Dicaprylyl Ether, Potassium Cetyl Phosphate, Glyceryl Stearate Se, Dimethicone, Helianthus Annuus (Sunflower) Seed Oil, Panax Ginseng Root Extract, Rosmarinus Officinalis (Rosemary) Leaf Extract, Aloe Barbadensis Leaf Juice, Caprylyl Glycol, Ethylhexylglycerin, Chlorphenesin, Glyceryl Caprylate, Acrylates/C10-30 Alkyl Acrylate Crosspolymer, Lauryl Laurate, Sodium Hydroxide, Phenethyl Alcohol, Glycerin, Tocopherol, Citric Acid, Potassium Sorbate, Sodium Benzoate, Coumarin.",
        "n_loves": "1.8K",
        "categories": [
            "Bath & Body",
            "Body Moisturizers",
            "Hand Cream & Foot Cream"
        ]
    },
    {
        "url": "https://www.sephora.com/ca/en/product/miniature-set-P507134",
        "error": "",
        "scrape_timestamp": "08/21/2023, 23:20:20",
        "product_name": "Miniature Set",
        "brand_name": "KAYALI",
        "options": [],
        "rating": "",
        "product_reviews": "",
        "ingredients": "Vanilla 28 Eau de Parfum:SD Alcohol 40-B/Alcohol Denat., Fragrance/Parfum, Water/Aqua/Eau, Butyl Methoxydibenzoylmethane, Alcohol, Tris(Tetramethylhydroxypiperidinol) Citrate, Ci 19140 (Yellow 5), Ci 60730 (Violet 2), Ci 14700 (Red 4), Citronellol, Coumarin, Limonene, Benzyl Salicylate.Eden Juicy Apple Eau de Parfum:SD Alcohol 40-B/Alcohol Denat., Fragrance/Parfum, Water/Aqua/Eau, Linalool, Ethylhexyl Methoxycinnamate, Ethylhexyl Salicylate, Butyl Methoxydibenzoylmethane, BHT, Citral, Citronellol, Geraniol, Hydroxycitronellal, Limonene, Benzyl Salicylate.D\u00e9j\u00e0 Vu White Flower 57 Eau de Parfum: SD Alcohol 40-B/Alcohol Denat., Fragrance/Parfum, Water/Aqua/Eau, Avobenzone/Butyl Methoxydibenzoylmethane, Alcohol, Tris(Tetramethylhydroxypiperidinol) Citrate, Yellow 5/ Ci 19140, Ext. Violet 2/Ci 60730, Red 4/Ci 14700, Citral, Citronellol, Eugenol, Farnesol, Geraniol, Hydroxycitronellal, Isoeugenol, Limonene, Linalool, Benzyl Alcohol, Benzyl Benzoate.Invite Only Amber 23 Eau de Parfum Intense:Alcohol Denat./SD Alcohol 40-B, Fragrance/Parfum, Water/Aqua/Eau, Avobenzone/Butyl Methoxydibenzoylmethane, Alcohol, Tris (Tetramethylhydroxypiperidinol) Citrate, Alpha-Isomethyl Ionone, Benzyl Benzoate, Cinnamal, Cinnamyl Alcohol, Coumarin, Linalool, Red 4/Ci 14700, Blue 1/Ci 42090, Ext. Violet 2/Ci 60730.",
        "n_loves": "1.5K",
        "categories": [
            "Fragrance",
            "Value & Gift Sets",
            "Perfume Gift Sets"
        ]
    },
    {
        "url": "https://www.sephora.com/ca/en/product/huda-beauty-kayali-eden-juicy-apple-%7C-01-travel-spray-P479718",
        "error": "",
        "scrape_timestamp": "08/21/2023, 23:20:30",
        "product_name": "EDEN JUICY APPLE  | 01 Travel Spray",
        "brand_name": "KAYALI",
        "options": [
            {
                "swatch_group": "Mini size",
                "flag_label": null,
                "size": null,
                "name": [
                    "Size: 0.33 oz/ 10 mL"
                ],
                "price": [
                    "$36.00"
                ],
                "sku": "Item 2493930"
            },
            {
                "swatch_group": "Mini size",
                "flag_label": null,
                "size": null,
                "name": [
                    "Size: .34 oz / 10 mL"
                ],
                "price": [
                    "$33.00"
                ],
                "sku": "Item 2599983"
            }
        ],
        "rating": "width:77.246%",
        "product_reviews": "610",
        "ingredients": "Sd Alcohol 40-B/Alcohol Denat., Fragrance/Parfum, Water/Aqua/Eau, Linalool, Ethylhexyl Methoxycinnamate, Ethylhexyl Salicylate, Butyl Methoxydibenzoylmethane, Bht, Citral, Citronellol, Geraniol, Hydroxycitronellal, Limonene, Benzyl Salicylate.",
        "n_loves": "47.6K",
        "categories": [
            "Fragrance",
            "Women",
            "Rollerballs & Travel Size"
        ]
    },
    {
        "url": "https://www.sephora.com/ca/en/product/huda-beauty-kayali-deja-vu-white-flower-57-P455258",
        "error": "",
        "scrape_timestamp": "08/21/2023, 23:20:44",
        "product_name": "D\u00c9J\u00c0 VU WHITE FLOWER | 57",
        "brand_name": "KAYALI",
        "options": [
            {
                "swatch_group": "Standard size",
                "flag_label": null,
                "size": null,
                "name": [
                    "Size: 1.7oz/50mL"
                ],
                "price": [
                    "$119.00"
                ],
                "sku": "Item 2328516"
            },
            {
                "swatch_group": "Standard size",
                "flag_label": null,
                "size": null,
                "name": [
                    "Size: 3.4 oz/ 100 mL"
                ],
                "price": [
                    "$168.00"
                ],
                "sku": "Item 2373603"
            },
            {
                "swatch_group": "Mini size",
                "flag_label": null,
                "size": null,
                "name": [
                    "Size: 0.33 oz/ 10 mL"
                ],
                "price": [
                    "$36.00"
                ],
                "sku": "Item 2411254"
            },
            {
                "swatch_group": "Mini size",
                "flag_label": null,
                "size": null,
                "name": [
                    "Size: .34 oz / 10 mL eau de parfum spray"
                ],
                "price": [
                    "$33.00"
                ],
                "sku": "Item 2599918"
            }
        ],
        "rating": "width:82.976%",
        "product_reviews": "168",
        "ingredients": "Sd Alcohol 40-B/Alcohol Denat., Fragrance/Parfum, Water/Aqua/Eau, Avobenzone/Butyl Methoxydibenzoylmethane, Alcohol, Tris(Tetramethylhydroxypiperidinol) Citrate, Yellow 5 / Ci 19140, Ext. Violet 2 / Ci 60730, Red 4 / Ci 14700, Citral, Citronellol, Eugenol, Farnesol, Geraniol, Hydroxycitronellal, Isoeugenol, Limonene, Linalool, Benzyl Alcohol, Benzyl Benzoate.70% Alcohol",
        "n_loves": "19.5K",
        "categories": [
            "Fragrance",
            "Women",
            "Perfume"
        ]
    },
    {
        "url": "https://www.sephora.com/ca/en/product/huda-beauty-kayali-vanilla-%7C-28-musk-%7C-12-doublesided-travel-rollerball-P463451",
        "error": "",
        "scrape_timestamp": "08/21/2023, 23:20:58",
        "product_name": "VANILLA | 28 & MUSK | 12 Doublesided Travel Rollerball",
        "brand_name": "KAYALI",
        "options": [
            {
                "swatch_group": "Standard size",
                "flag_label": null,
                "size": null,
                "name": [
                    "Size: 2 x 5 mL"
                ],
                "price": [
                    "$36.00"
                ],
                "sku": "Item 2328524"
            }
        ],
        "rating": "width:84.19399999999999%",
        "product_reviews": "62",
        "ingredients": "VANILLA | 28:Sd Alcohol 40-B/Alcohol Denat., Fragrance/Parfum, Water / Aqua / Eau, Butyl Methoxydibenzoylmethane, Alcohol, Tris(Tetramethylhydroxypiperidinol) Citrate, Ci 19140 (Yellow 5), Ci 60730 (Violet 2), Ci 14700 (Red 4), Citronellol, Coumarin, Limonene, Benzyl Salicylate, Butylphenyl Methylpropional.\u200bMUSK | 12:Sd Alcohol 40-B/Alcohol Denat., Fragrance/Parfum, Water / Aqua / Eau, Ethylhexyl Methoxycinnamate, Ethylhexyl Salicylate, Butyl Methoxydibenzoylmethane, Alcohol, Tris(Tetramethylhydroxypiperidinol)Citrate, Ci 60730 (Violet 2), Bht, Ci 19140 (Yellow 5), Ci 14700 (Red 4), Alpha-Isomethyl Ionone, Coumarin, Butylphenyl Methylpropional.Please note that ingredient lists may change or vary from time to time. Please refer to the ingredient list on the product packaging you receive for the most up-to-date list of ingredients.",
        "n_loves": "14.8K",
        "categories": [
            "Fragrance",
            "Women",
            "Rollerballs & Travel Size"
        ]
    },
    {
        "url": "https://www.sephora.com/ca/en/product/kayali-vanilla-P439406",
        "error": "",
        "scrape_timestamp": "08/21/2023, 23:21:11",
        "product_name": "VANILLA | 28",
        "brand_name": "KAYALI",
        "options": [
            {
                "swatch_group": "Standard size",
                "flag_label": "OUT OF STOCK",
                "size": null,
                "name": [
                    "Size: 1.7 oz / 50 ml eau de parfum spray",
                    "OUT OF STOCK"
                ],
                "price": [
                    "$119.00"
                ],
                "sku": "Item 2224491"
            },
            {
                "swatch_group": "Standard size",
                "flag_label": null,
                "size": null,
                "name": [
                    "Size: 3.4 oz/100 mL"
                ],
                "price": [
                    "$168.00"
                ],
                "sku": "Item 2163970"
            },
            {
                "swatch_group": "Mini size",
                "flag_label": null,
                "size": null,
                "name": [
                    "Size: .34 oz / 10 mL eau de parfum spray"
                ],
                "price": [
                    "$33.00"
                ],
                "sku": "Item 2599900"
            }
        ],
        "rating": "width:77.40400000000001%",
        "product_reviews": "1.1K",
        "ingredients": "Sd Alcohol 40-B/Alcohol Denat., Fragrance/Parfum, Water / Aqua / Eau, Butyl Methoxydibenzoylmethane, Alcohol, Tris(Tetramethylhydroxypiperidinol) Citrate, Ci 19140 (Yellow 5), Ci 60730 (Violet 2), Ci 14700 (Red 4), Citronellol, Coumarin, Limonene, Benzyl Salicylate",
        "n_loves": "142.2K",
        "categories": [
            "Fragrance",
            "Women",
            "Perfume"
        ]
    },
    {
        "url": "https://www.sephora.com/ca/en/product/huda-beauty-kayali-invite-only-amber-%7C-23-P474055",
        "error": "",
        "scrape_timestamp": "08/21/2023, 23:21:24",
        "product_name": "INVITE ONLY AMBER | 23",
        "brand_name": "KAYALI",
        "options": [
            {
                "swatch_group": "Standard size",
                "flag_label": null,
                "size": null,
                "name": [
                    "Size: 1.7 oz/ 50 mL"
                ],
                "price": [
                    "$135.00"
                ],
                "sku": "Item 2373611"
            },
            {
                "swatch_group": "Standard size",
                "flag_label": null,
                "size": null,
                "name": [
                    "Size: 3.4 oz/ 100 mL"
                ],
                "price": [
                    "$185.00"
                ],
                "sku": "Item 2476281"
            },
            {
                "swatch_group": "Mini size",
                "flag_label": null,
                "size": null,
                "name": [
                    "Size: 0.34 oz/ 10 mL"
                ],
                "price": [
                    "$36.00"
                ],
                "sku": "Item 2476299"
            },
            {
                "swatch_group": "Mini size",
                "flag_label": null,
                "size": null,
                "name": [
                    "Size: .34 oz / 10 mL"
                ],
                "price": [
                    "$33.00"
                ],
                "sku": "Item 2599975"
            }
        ],
        "rating": "width:69.08999999999999%",
        "product_reviews": "198",
        "ingredients": "Alcohol Denat./Sd Alcohol 40-B, Fragrance/Parfum, Water/Aqua/Eau, Avobenzone/Butyl Methoxydibenzoylmethane, Alcohol, Tris (Tetramethylhydroxypiperidinol) Citrate, Alpha-Isomethyl Ionone, Benzyl Benzoate, Cinnamal, Cinnamyl Alcohol, Coumarin, Linalool, Red 4/Ci 14700, Blue 1/Ci 42090, Ext. Violet 2/Ci 60730.",
        "n_loves": "22.9K",
        "categories": [
            "Fragrance",
            "Women",
            "Perfume"
        ]
    },
    {
        "url": "https://www.sephora.com/ca/en/product/yum-pistachio-gelato-power-duo-P506815",
        "error": "",
        "scrape_timestamp": "08/21/2023, 23:21:37",
        "product_name": "YUM PISTACHIO GELATO POWER DUO",
        "brand_name": "KAYALI",
        "options": [],
        "rating": "width:80%",
        "product_reviews": "5",
        "ingredients": "YUM PISTACHIO GELATO 33 EDP INTENSE:SD Alcohol 40-B/Alcohol Denat., Fragrance/Parfum, Water/Aqua/Eau, Limonene, Coumarin, Butyl Methoxydibenzoylmethane, Alcohol, Tris(Tetramethylhydroxypiperidinol) Citrate, Alpha-Isomethyl Ionone, Cinnamyl Alcohol, Linalool, Benzyl Alcohol, Benzyl Benzoate, Citral, Citronellol, Farnesol, Geraniol, Hydroxycitronellal, Blue 1/CI 42090.Liquid Matte Ultra-Comfort Transfer-proof Lipstick:Isododecane, Cyclopentasiloxane, Synthetic Beeswax, Trimethylsiloxysilicate, Polypropylsilsesquioxane, Octyldodecanol, Disteardimonium Hectorite, Mica, Alcohol, Ethyl Vanillin, Propylene Carbonate, Caprylyl Glycol, Flavor/Aroma, Glycerin, Caprylhydroxamic Acid, Water/Aqua/Eau, Phospholipids, Coffea Arabica (Coffee) Seed Extract, Olea Europaea (Olive) Fruit Oil, Ascorbyl Palmitate, Linoleic Acid, Retinyl Palmitate, Tocopheryl Acetate, Lycopene. May Contain (+/-) Iron Oxides (CI 77491, CI 77492, CI 77499), Titanium Dioxide (CI 77891), Yellow 5 Lake (CI 19140), Red 6 (CI 15850), Red 6 Lake (CI 15850), Red 7 Lake (CI 15850), Red 28 Lake (CI 45410), Blue 1 Lake (CI 42090).",
        "n_loves": "4.3K",
        "categories": [
            "Fragrance",
            "Value & Gift Sets",
            "Perfume Gift Sets"
        ]
    },
    {
        "url": "https://www.sephora.com/ca/en/product/huda-beauty-kayali-eden-juicy-apple-%7C-01-P479717",
        "error": "",
        "scrape_timestamp": "08/21/2023, 23:21:47",
        "product_name": "EDEN JUICY APPLE | 01",
        "brand_name": "KAYALI",
        "options": [
            {
                "swatch_group": "Standard size",
                "flag_label": null,
                "size": null,
                "name": [
                    "Size: 1.7 oz/ 50 mL Eau de Parfum Spray"
                ],
                "price": [
                    "$120.00"
                ],
                "sku": "Item 2493948"
            },
            {
                "swatch_group": "Standard size",
                "flag_label": "ONLY A FEW LEFT",
                "size": null,
                "name": [
                    "Size: 3.4 oz/ 100 mL",
                    "ONLY A FEW LEFT"
                ],
                "price": [
                    "$169.00"
                ],
                "sku": "Item 2493955"
            },
            {
                "swatch_group": "Mini size",
                "flag_label": null,
                "size": null,
                "name": [
                    "Size: 0.33 oz/ 10 mL"
                ],
                "price": [
                    "$36.00"
                ],
                "sku": "Item 2493930"
            },
            {
                "swatch_group": "Mini size",
                "flag_label": null,
                "size": null,
                "name": [
                    "Size: .34 oz / 10 mL"
                ],
                "price": [
                    "$33.00"
                ],
                "sku": "Item 2599983"
            }
        ],
        "rating": "width:77.246%",
        "product_reviews": "610",
        "ingredients": "Sd Alcohol 40-B/Alcohol Denat., Fragrance/Parfum, Water/Aqua/Eau, Linalool, Ethylhexyl Methoxycinnamate, Ethylhexyl Salicylate, Butyl Methoxydibenzoylmethane, Bht, Citral, Citronellol, Geraniol, Hydroxycitronellal, Limonene, Benzyl Salicylate.",
        "n_loves": "49.1K",
        "categories": [
            "Fragrance",
            "Women",
            "Perfume"
        ]
    },
    {
        "url": "https://www.sephora.com/ca/en/product/huda-beauty-kayali-deja-vu-white-flower-hair-mist-P462863",
        "error": "",
        "scrape_timestamp": "08/21/2023, 23:22:01",
        "product_name": "D\u00c9J\u00c0 VU WHITE FLOWER Hair Mist",
        "brand_name": "KAYALI",
        "options": [
            {
                "swatch_group": "Standard size",
                "flag_label": null,
                "size": null,
                "name": [
                    "Size: 2.54 oz/ 75 mL"
                ],
                "price": [
                    "$58.00"
                ],
                "sku": "Item 2373595"
            }
        ],
        "rating": "width:85.45400000000001%",
        "product_reviews": "55",
        "ingredients": "Water/Aqua/Eau, Fragrance/Parfum, Peg-40 Hydrogenated Castor Oil, Hydrogenated Starch Hydrolysate, Phenoxyethanol, Panthenol, Chlorphenesin, Glycerin, Aloe Barbadensis Leaf Juice Powder, Camellia Oleifera Seed Oil, Syringa Vulgaris (Lilac) Extract, Sodium Hydroxide, Tocopherol, Anise Alcohol, Methyl Benzoate, Benzoic Acid, Bht, Ethyl Benzoate, Benzyl Alcohol, Benzyl Benzoate, Citronellol, Farnesol, Geraniol, Isoeugenol, Linalool.",
        "n_loves": "11.7K",
        "categories": [
            "Fragrance",
            "Women",
            "Body Mist & Hair Mist"
        ]
    },
    {
        "url": "https://www.sephora.com/ca/en/product/kayali-citrus-P439403",
        "error": "",
        "scrape_timestamp": "08/21/2023, 23:22:13",
        "product_name": "CITRUS | 08",
        "brand_name": "KAYALI",
        "options": [
            {
                "swatch_group": "Standard size",
                "flag_label": "ONLY A FEW LEFT",
                "size": null,
                "name": [
                    "Size: 1.7oz/50mL",
                    "ONLY A FEW LEFT"
                ],
                "price": [
                    "$119.00"
                ],
                "sku": "Item 2224509"
            },
            {
                "swatch_group": "Standard size",
                "flag_label": "ONLY A FEW LEFT",
                "size": null,
                "name": [
                    "Size: 3.4 oz/100 mL",
                    "ONLY A FEW LEFT"
                ],
                "price": [
                    "$168.00"
                ],
                "sku": "Item 2163988"
            }
        ],
        "rating": "width:80.5%",
        "product_reviews": "160",
        "ingredients": "Sd Alcohol 40-B/Alcohol Denat., Fragrance/Parfum, Water / Aqua / Eau, Ethylhexyl Methoxycinnamate, Ethylhexyl Salicylate, Butyl Methoxydibenzoylmethane, Alcohol, Tris(Tetramethylhydroxypiperidinol)Citrate, Bht, Ci 19140 (Yellow 5), Ci 14700 (Red 4), Ci 60730 (Violet 2), Citral, Citronellol, Coumarin, Eugenol, Geraniol, Limonene, Linalool.",
        "n_loves": "8.9K",
        "categories": [
            "Fragrance",
            "Women",
            "Perfume"
        ]
    },
    {
        "url": "https://www.sephora.com/ca/en/product/lovefest-eau-de-parfum-intense-P501018",
        "error": "",
        "scrape_timestamp": "08/21/2023, 23:22:26",
        "product_name": "LOVEFEST BURNING CHERRY | 48",
        "brand_name": "KAYALI",
        "options": [
            {
                "swatch_group": "Standard size",
                "flag_label": null,
                "size": null,
                "name": [
                    "Size: 1.7 oz / 50 mL"
                ],
                "price": [
                    "$119.00"
                ],
                "sku": "Item 2599942"
            },
            {
                "swatch_group": "Standard size",
                "flag_label": "OUT OF STOCK",
                "size": null,
                "name": [
                    "Size: 3.4 oz / 100 mL eau de parfum spray",
                    "OUT OF STOCK"
                ],
                "price": [
                    "$168.00"
                ],
                "sku": "Item 2611465"
            },
            {
                "swatch_group": "Mini size",
                "flag_label": null,
                "size": null,
                "name": [
                    "Size: .33 oz / 10 mL"
                ],
                "price": [
                    "$33.00"
                ],
                "sku": "Item 2599934"
            }
        ],
        "rating": "width:76.888%",
        "product_reviews": "495",
        "ingredients": "Sd Alcohol 40-B/Alcohol Denat., Fragrance/Parfum, Water/Aqua/Eau, Citral, Citronellol, Coumarin, Eugenol, Geraniol, Hydroxycitronellal, Isoeugenol, Limonene, Linalool, Anise Alcohol, Benzyl Alcohol, Benzyl Benzoate, Benzyl Cinnamate, Benzyl Salicylate. 70%",
        "n_loves": "47.1K",
        "categories": [
            "Fragrance",
            "Women",
            "Perfume"
        ]
    },
    {
        "url": "https://www.sephora.com/ca/en/product/huda-beauty-kayali-d-eacute-j-agrave-vu-white-flower-%7C-57-travel-spray-P468446",
        "error": "",
        "scrape_timestamp": "08/21/2023, 23:22:40",
        "product_name": "D\u00c9J\u00c0 VU WHITE FLOWER | 57 Travel Spray",
        "brand_name": "KAYALI",
        "options": [
            {
                "swatch_group": "Mini size",
                "flag_label": null,
                "size": null,
                "name": [
                    "Size: 0.33 oz/ 10 mL"
                ],
                "price": [
                    "$36.00"
                ],
                "sku": "Item 2411254"
            },
            {
                "swatch_group": "Mini size",
                "flag_label": null,
                "size": null,
                "name": [
                    "Size: .34 oz / 10 mL eau de parfum spray"
                ],
                "price": [
                    "$33.00"
                ],
                "sku": "Item 2599918"
            }
        ],
        "rating": "width:82.976%",
        "product_reviews": "168",
        "ingredients": "Sd Alcohol 40-B/Alcohol Denat., Fragrance/Parfum, Water/Aqua/Eau, Avobenzone/Butyl Methoxydibenzoylmethane, Alcohol, Tris(Tetramethylhydroxypiperidinol) Citrate, Yellow 5 / Ci 19140, Ext. Violet 2 / Ci 60730, Red 4 / Ci 14700, Citral, Citronellol, Eugenol, Farnesol, Geraniol, Hydroxycitronellal, Isoeugenol, Limonene, Linalool, Benzyl Alcohol, Benzyl Benzoate.70% Alcohol ",
        "n_loves": "16.9K",
        "categories": [
            "Fragrance",
            "Women",
            "Rollerballs & Travel Size"
        ]
    },
    {
        "url": "https://www.sephora.com/ca/en/product/huda-beauty-kayali-invite-only-amber-%7C-23-travel-spray-P474056",
        "error": "",
        "scrape_timestamp": "08/21/2023, 23:22:53",
        "product_name": "INVITE ONLY AMBER | 23  Travel Spray",
        "brand_name": "KAYALI",
        "options": [
            {
                "swatch_group": "Mini size",
                "flag_label": null,
                "size": null,
                "name": [
                    "Size: 0.34 oz/ 10 mL"
                ],
                "price": [
                    "$36.00"
                ],
                "sku": "Item 2476299"
            },
            {
                "swatch_group": "Mini size",
                "flag_label": null,
                "size": null,
                "name": [
                    "Size: .34 oz / 10 mL"
                ],
                "price": [
                    "$33.00"
                ],
                "sku": "Item 2599975"
            }
        ],
        "rating": "width:60.285999999999994%",
        "product_reviews": "70",
        "ingredients": "Alcohol Denat./Sd Alcohol 40-B, Fragrance/Parfum, Water/Aqua/Eau, Avobenzone/Butyl Methoxydibenzoylmethane, Alcohol, Tris (Tetramethylhydroxypiperidinol) Citrate, Alpha-Isomethyl Ionone, Benzyl Benzoate, Cinnamal, Cinnamyl Alcohol, Coumarin, Linalool, Red 4/Ci 14700, Blue 1/Ci 42090, Ext. Violet 2/Ci 60730.",
        "n_loves": "20.6K",
        "categories": [
            "Fragrance",
            "Women",
            "Rollerballs & Travel Size"
        ]
    },
    {
        "url": "https://www.sephora.com/ca/en/product/kayali-elixir-P439404",
        "error": "",
        "scrape_timestamp": "08/21/2023, 23:23:05",
        "product_name": "ELIXIR | 11",
        "brand_name": "KAYALI",
        "options": [
            {
                "swatch_group": "Standard size",
                "flag_label": null,
                "size": null,
                "name": [
                    "Size: 1.7oz/50mL"
                ],
                "price": [
                    "$119.00"
                ],
                "sku": "Item 2224475"
            },
            {
                "swatch_group": "Standard size",
                "flag_label": "ONLY A FEW LEFT",
                "size": null,
                "name": [
                    "Size: 3.4 oz/100 mL",
                    "ONLY A FEW LEFT"
                ],
                "price": [
                    "$168.00"
                ],
                "sku": "Item 2163954"
            }
        ],
        "rating": "width:74.336%",
        "product_reviews": "286",
        "ingredients": " Sd Alcohol 40-B/Alcohol Denat., Fragrance/Parfum, Water / Aqua / Eau, Ethylhexyl Methoxycinnamate, Ethylhexyl Salicylate, Butyl Methoxydibenzoylmethane, Bht, Citral, Citronellol, Eugenol, Farnesol, Geraniol, Linalool, Benzyl Alcohol.",
        "n_loves": "18.1K",
        "categories": [
            "Fragrance",
            "Women",
            "Perfume"
        ]
    },
    {
        "url": "https://www.sephora.com/ca/en/product/huda-beauty-kayali-sweet-diamond-pink-pepper-%7C-25-travel-spray-P472036",
        "error": "",
        "scrape_timestamp": "08/21/2023, 23:23:18",
        "product_name": "SWEET DIAMOND PINK PEPPER  | 25 Travel Spray",
        "brand_name": "KAYALI",
        "options": [
            {
                "swatch_group": "Mini size",
                "flag_label": null,
                "size": null,
                "name": [
                    "Size: 0.33 oz/ 10 mL"
                ],
                "price": [
                    "$36.00"
                ],
                "sku": "Item 2411288"
            },
            {
                "swatch_group": "Mini size",
                "flag_label": null,
                "size": null,
                "name": [
                    "Size: .34 oz / 10 mL eau de parfum intense spray"
                ],
                "price": [
                    "$33.00"
                ],
                "sku": "Item 2599884"
            }
        ],
        "rating": "width:77.236%",
        "product_reviews": "152",
        "ingredients": "Alcohol Denat./Sd Alcohol 40-B, Fragrance/Parfum, Water/Aqua/Eau, Avobenzone/Butyl Methoxydibenzoylmethane, Alcohol, Tris (Tetramethylhydroxypiperidinol) Citrate, Citral, Citronellol, Eugenol, Geraniol, Isoeugenol, Limonene, Linalool, Benzyl Salicylate, Ext. Violet 2/Ci 60730, Red 4/Ci 14700, Yellow 5/Ci 19140.",
        "n_loves": "20.5K",
        "categories": [
            "Fragrance",
            "Women",
            "Rollerballs & Travel Size"
        ]
    },
    {
        "url": "https://www.sephora.com/ca/en/product/kayali-musk-P439405",
        "error": "",
        "scrape_timestamp": "08/21/2023, 23:23:31",
        "product_name": "MUSK | 12",
        "brand_name": "KAYALI",
        "options": [
            {
                "swatch_group": "Standard size",
                "flag_label": "ONLY A FEW LEFT",
                "size": null,
                "name": [
                    "Size: 1.7oz/50mL",
                    "ONLY A FEW LEFT"
                ],
                "price": [
                    "$119.00"
                ],
                "sku": "Item 2224483"
            },
            {
                "swatch_group": "Mini size",
                "flag_label": null,
                "size": null,
                "name": [
                    "Size: .34 oz / 10 mL"
                ],
                "price": [
                    "$33.00"
                ],
                "sku": "Item 2599876"
            }
        ],
        "rating": "width:76.138%",
        "product_reviews": "233",
        "ingredients": " Sd Alcohol 40-B/Alcohol Denat., Fragrance/Parfum, Water / Aqua / Eau, Ethylhexyl Methoxycinnamate, Ethylhexyl Salicylate, Butyl Methoxydibenzoylmethane, Alcohol, Tris(Tetramethylhydroxypiperidinol)Citrate, Ci 60730 (Violet 2), Bht, Ci 19140 (Yellow 5), Ci 14700 (Red 4), Alpha-Isomethyl Ionone, Coumarin, Butylphenyl Methylpropional.",
        "n_loves": "15.4K",
        "categories": [
            "Fragrance",
            "Women",
            "Perfume"
        ]
    },
    {
        "url": "https://www.sephora.com/ca/en/product/vanilla-royale-sugared-patchouli-|-64-eau-de-parfum-intense-P502074",
        "error": "",
        "scrape_timestamp": "08/21/2023, 23:23:43",
        "product_name": "Vanilla Royale Sugared Patchouli | 64 Eau de Parfum Intense",
        "brand_name": "KAYALI",
        "options": [
            {
                "swatch_group": "Standard size",
                "flag_label": null,
                "size": null,
                "name": [
                    "Size: 1.7 oz / 50 mL"
                ],
                "price": [
                    "$135.00"
                ],
                "sku": "Item 2599967"
            },
            {
                "swatch_group": "Mini size",
                "flag_label": null,
                "size": null,
                "name": [
                    "Size: .34 oz / 10 mL"
                ],
                "price": [
                    "$33.00"
                ],
                "sku": "Item 2599959"
            }
        ],
        "rating": "width:76.96%",
        "product_reviews": "125",
        "ingredients": "Sd Alcohol 40-B/Alcohol Denat., Fragrance/Parfum, Water/Aqua/Eau, Ethylhexyl Methoxycinnamate, Ethylhexyl Salicylate, Butyl Methoxydibenzoylmethane, Cinnamyl Alcohol, Citronellol, Coumarin, Eugenol, Geraniol, Isoeugenol, Limonene, Linalool.",
        "n_loves": "24.5K",
        "categories": [
            "Fragrance",
            "Women",
            "Perfume"
        ]
    },
    {
        "url": "https://www.sephora.com/ca/en/product/lovefest-eau-de-parfum-intense-travel-spray-P500987",
        "error": "",
        "scrape_timestamp": "08/21/2023, 23:23:56",
        "product_name": "Lovefest Burning Cherry | 48 Travel Spray",
        "brand_name": "KAYALI",
        "options": [
            {
                "swatch_group": "Mini size",
                "flag_label": null,
                "size": null,
                "name": [
                    "Size: .33 oz / 10 mL"
                ],
                "price": [
                    "$33.00"
                ],
                "sku": "Item 2599934"
            }
        ],
        "rating": "width:76.888%",
        "product_reviews": "495",
        "ingredients": "Sd Alcohol 40-B/Alcohol Denat., Fragrance/Parfum, Water/Aqua/Eau, Citral, Citronellol, Coumarin, Eugenol, Geraniol, Hydroxycitronellal, Isoeugenol, Limonene, Linalool, Anise Alcohol, Benzyl Alcohol, Benzyl Benzoate, Benzyl Cinnamate, Benzyl Salicylate. 70%",
        "n_loves": "34.5K",
        "categories": [
            "Fragrance",
            "Women",
            "Rollerballs & Travel Size"
        ]
    }
]