[
    {
        "url": "https://www.sephora.com/ca/en/product/flowerbomb-eau-de-parfum-duo-P501000",
        "error": "",
        "scrape_timestamp": "08/22/2023, 21:19:02",
        "product_name": "Flowerbomb Eau de Parfum Duo",
        "brand_name": "Viktor&Rolf",
        "options": [],
        "rating": "width:68.88799999999999%",
        "product_reviews": "9",
        "ingredients": "Alcohol, Parfum / Fragrance, Aqua / Water, Benzyl Salicylate, Linalool, Butyl Methoxydibenzoylmethane, Ethylhexyl Methoxycinnamate, Limonene, Pentaerythrityl Tetra-Di-T-Butyl Hydroxyhydrocinnamate, Coumarin, Benzyl Alcohol, Benzyl Benzoate, Citral, Ci 19140 / Yellow 5, Ci 60730 / Ext. Violet 2, Ci 17200 / Red 33.",
        "n_loves": "5K",
        "categories": [
            "Fragrance",
            "Value & Gift Sets",
            "Perfume Gift Sets"
        ]
    },
    {
        "url": "https://www.sephora.com/ca/en/product/mini-flowerbomb-eau-de-parfum-set-P505941",
        "error": "",
        "scrape_timestamp": "08/22/2023, 21:19:12",
        "product_name": "Mini Flowerbomb Eau de Parfum Set",
        "brand_name": "Viktor&Rolf",
        "options": [],
        "rating": "width:95%",
        "product_reviews": "8",
        "ingredients": "Unknown Ingredients",
        "n_loves": "10.7K",
        "categories": [
            "Fragrance",
            "Value & Gift Sets",
            "Perfume Gift Sets"
        ]
    },
    {
        "url": "https://www.sephora.com/ca/en/product/bonbon-P397836",
        "error": "",
        "scrape_timestamp": "08/22/2023, 21:19:24",
        "product_name": "BONBON",
        "brand_name": "Viktor&Rolf",
        "options": [
            {
                "swatch_group": "Standard size",
                "flag_label": null,
                "size": null,
                "name": [
                    "Size: 1 oz/ 30 mL"
                ],
                "price": [
                    "$120.00"
                ],
                "sku": "Item 1619956"
            },
            {
                "swatch_group": "Standard size",
                "flag_label": "ONLY A FEW LEFT",
                "size": null,
                "name": [
                    "Size: 1.7 oz/ 50 mL",
                    "ONLY A FEW LEFT"
                ],
                "price": [
                    "$163.00"
                ],
                "sku": "Item 1619964"
            },
            {
                "swatch_group": "Standard size",
                "flag_label": "ONLY A FEW LEFT",
                "size": null,
                "name": [
                    "Size: 3.04 oz/ 90 mL",
                    "ONLY A FEW LEFT"
                ],
                "price": [
                    "$210.00"
                ],
                "sku": "Item 1619972"
            }
        ],
        "rating": "width:87.24399999999999%",
        "product_reviews": "312",
        "ingredients": "Alcohol, Parfum / Fragrance, Aqua / Water, Benzyl Salicylate, Limonene, Linalool, Benzyl Alcohol, Hydroxycitronellal, Ethylhexyl Methoxycinnamate, Alpha-Isomethyl Ionone, Coumarin, Citronellol, Butyl Methoxydibenzoylmethane, Ethylhexyl Salicylate, Bht, Geraniol, Citral, Farnesol, Benzyl Benzoate, Ci 60730 / Ext. Violet 2, Ci 47005 / Yellow 10.",
        "n_loves": "47.2K",
        "categories": [
            "Fragrance",
            "Women",
            "Perfume"
        ]
    },
    {
        "url": "https://www.sephora.com/ca/en/product/mini-flowerbomb-perfume-trio-set-P505930",
        "error": "",
        "scrape_timestamp": "08/22/2023, 21:19:40",
        "product_name": "Mini Flowerbomb Perfume Trio Set",
        "brand_name": "Viktor&Rolf",
        "options": [],
        "rating": "width:92.5%",
        "product_reviews": "8",
        "ingredients": "Alcohol, Parfum/Fragrance, Aqua/Water, Benzyl Salicylate, Linalool, Butyl Methoxydibenzoylmethane, Ethylhexyl Methoxycinnamate, Limonene, Pentaerythrityl Tetra-Di-T-Butyl Hydroxyhydrocinnamate, Coumarin, Benzyl Alcohol, Benzyl Benzoate, Citral, CI 19140/Yellow 5, CI 60730/Ext. Violet 2, CI 17200/Red 33.",
        "n_loves": "11.4K",
        "categories": [
            "Fragrance",
            "Value & Gift Sets",
            "Perfume Gift Sets"
        ]
    },
    {
        "url": "https://www.sephora.com/ca/en/product/spicebomb-extreme-P405501",
        "error": "",
        "scrape_timestamp": "08/22/2023, 21:19:50",
        "product_name": "Spicebomb Extreme",
        "brand_name": "Viktor&Rolf",
        "options": [
            {
                "swatch_group": "Standard size",
                "flag_label": null,
                "size": null,
                "name": [
                    "Size: 3.04 oz/ 90 mL"
                ],
                "price": [
                    "$176.00"
                ],
                "sku": "Item 1798479"
            }
        ],
        "rating": "width:87.614%",
        "product_reviews": "176",
        "ingredients": "Alcohol, Parfum / Fragrance, Aqua / Water, Limonene, Coumarin, Ethylhexyl Methoxycinnamate, Linalool, Butyl Methoxydibenzoylmethane, Eugenol, Ethylhexyl Salicylate, Alpha-Isomethyl Ionone, Methyl Anthranilate, Citral, Citronellol, Benzyl Benzoate, Geraniol, Benzyl Alcohol, Isoeugenol, Ci 60730 / Ext. Violet 2.",
        "n_loves": "10K",
        "categories": [
            "Fragrance",
            "Men",
            "Cologne"
        ]
    },
    {
        "url": "https://www.sephora.com/ca/en/product/flowerbomb-nectar-P429082",
        "error": "",
        "scrape_timestamp": "08/22/2023, 21:20:04",
        "product_name": "Flowerbomb Nectar",
        "brand_name": "Viktor&Rolf",
        "options": [
            {
                "swatch_group": "Standard size",
                "flag_label": null,
                "size": null,
                "name": [
                    "Size: 1.7 oz/ 50 mL"
                ],
                "price": [
                    "$163.00"
                ],
                "sku": "Item 2042984"
            }
        ],
        "rating": "width:89.24799999999999%",
        "product_reviews": "372",
        "ingredients": "Alcohol, Parfum/Fragrance, Aqua/Water, Linalool, Limonene, Benzyl Salicylate, Benzyl Alcohol, Citronellol, Coumarin, Alpha-Isomethyl Ionone, Methyl Anthranilate, Citral, Geraniol, Ci 60730/Ext. Violet 2, Ci 14700/Red 4.",
        "n_loves": "45K",
        "categories": [
            "Fragrance",
            "Women",
            "Perfume"
        ]
    },
    {
        "url": "https://www.sephora.com/ca/en/product/flowerbomb-mini-P426305",
        "error": "",
        "scrape_timestamp": "08/22/2023, 21:20:18",
        "product_name": "Flowerbomb Mini",
        "brand_name": "Viktor&Rolf",
        "options": [
            {
                "swatch_group": "Mini size",
                "flag_label": null,
                "size": null,
                "name": [
                    "Size: 0.68 oz/ 20 mL"
                ],
                "price": [
                    "$75.00"
                ],
                "sku": "Item 1233121"
            }
        ],
        "rating": "width:91.7%",
        "product_reviews": "5K",
        "ingredients": "Alcohol, Parfum/Fragrance, Aqua/Water, Benzyl Salicylate, Linalool, Butyl Methoxydibenzoylmethane, Ethylhexyl Methoxycinnamate, Limonene, Pentaerythrityl Tetra-Di-T-Butyl Hydroxyhydrocinnamate, Coumarin, Benzyl Alcohol, Benzyl Benzoate, Citral, Ci 19140/Yellow 5, Ci 60730/Ext. Violet 2, Ci 17200/Red 33.",
        "n_loves": "34.2K",
        "categories": [
            "Fragrance"
        ]
    },
    {
        "url": "https://www.sephora.com/ca/en/product/viktor-rolf-spicebomb-night-vision-eau-de-parfum-P466160",
        "error": "",
        "scrape_timestamp": "08/22/2023, 21:20:31",
        "product_name": "Spicebomb Night Vision Eau de Parfum",
        "brand_name": "Viktor&Rolf",
        "options": [
            {
                "swatch_group": "Standard size",
                "flag_label": "ONLY A FEW LEFT",
                "size": null,
                "name": [
                    "Size: 1.6 oz/ 50 ml",
                    "ONLY A FEW LEFT"
                ],
                "price": [
                    "$136.00"
                ],
                "sku": "Item 2387074"
            }
        ],
        "rating": "width:86.66600000000001%",
        "product_reviews": "3",
        "ingredients": "Alcohol, Parfum / Fragrance, Aqua / Water / Eau, Benzyl Salicylate, Linalool, Limonene, Benzyl Alcohol, Ethylhexyl Salicylate, Butyl Methoxydibenzoylmethane, Coumarin, Citronellol, Hydroxycitronellal, Benzyl Benzoate, Alpha-Isomethyl Ionone, Benzyl Cinnamate, Citral, Eugenol, Geraniol, Cinnamal.",
        "n_loves": "247",
        "categories": [
            "Fragrance",
            "Women",
            "Perfume"
        ]
    },
    {
        "url": "https://www.sephora.com/ca/en/product/viktor-rolf-flowerbomb-ruby-orchid-eau-de-parfum-travel-spray-P479474",
        "error": "",
        "scrape_timestamp": "08/22/2023, 21:20:44",
        "product_name": "Flowerbomb Ruby Orchid Eau de Parfum Travel Spray",
        "brand_name": "Viktor&Rolf",
        "options": [
            {
                "swatch_group": "Mini size",
                "flag_label": null,
                "size": null,
                "name": [
                    "Size: 0.34 oz/ 10 mL"
                ],
                "price": [
                    "$43.00"
                ],
                "sku": "Item 2480598"
            }
        ],
        "rating": "width:90.108%",
        "product_reviews": "558",
        "ingredients": "Alcohol, Parfum/Fragrance, Aqua/Water/Eau, Linalool, Benzyl Salicylate, Benzyl Alcohol, Butyl Methoxydibenzoylmethane, Hydroxycitronellal, Limonene, Coumarin, Methyl Anthranilate, Isoeugenol, Benzyl Benzoate, Citronellol, Citral, C1 17200/Red 33, Ci 60730/Ext. Violet 2.",
        "n_loves": "21.7K",
        "categories": [
            "Fragrance",
            "Women",
            "Rollerballs & Travel Size"
        ]
    },
    {
        "url": "https://www.sephora.com/ca/en/product/viktor-rolf-spicebomb-infrared-eau-de-toilette-P472830",
        "error": "",
        "scrape_timestamp": "08/22/2023, 21:20:58",
        "product_name": "Spicebomb Infrared Eau de Toilette",
        "brand_name": "Viktor&Rolf",
        "options": [
            {
                "swatch_group": "Standard size",
                "flag_label": "ONLY A FEW LEFT",
                "size": null,
                "name": [
                    "Size: 1.7 oz/ 50 mL",
                    "ONLY A FEW LEFT"
                ],
                "price": [
                    "$132.00"
                ],
                "sku": "Item 2408359"
            },
            {
                "swatch_group": "Standard size",
                "flag_label": "ONLY A FEW LEFT",
                "size": null,
                "name": [
                    "Size: 3.0 oz/ 90 mL",
                    "ONLY A FEW LEFT"
                ],
                "price": [
                    "$163.00"
                ],
                "sku": "Item 2408367"
            }
        ],
        "rating": "width:89.65799999999999%",
        "product_reviews": "350",
        "ingredients": "Alcohol, Parfum/Fragrance, Aqua/Water, Limonene, Linalool, Butyl Methoxydibenzoylmethane, Coumarin, Ethylhexyl Salicylate, Cinnamyl Alcohol, Eugenol, Cinnamal, Citronellol, Methyl Anthranilate, Geraniol, Citral, Benzyl Benzoate, Isoeugenol.",
        "n_loves": "4.3K",
        "categories": [
            "Fragrance",
            "Men",
            "Cologne"
        ]
    },
    {
        "url": "https://www.sephora.com/ca/en/product/flowerbomb-P255506",
        "error": "",
        "scrape_timestamp": "08/22/2023, 21:21:13",
        "product_name": "Flowerbomb",
        "brand_name": "Viktor&Rolf",
        "options": [
            {
                "swatch_group": "Standard size",
                "flag_label": null,
                "size": null,
                "name": [
                    "Size: 1.7 oz/ 50 mL"
                ],
                "price": [
                    "$163.00"
                ],
                "sku": "Item 1233147"
            },
            {
                "swatch_group": "Standard size",
                "flag_label": null,
                "size": null,
                "name": [
                    "Size: 3.4 oz/ 100 mL"
                ],
                "price": [
                    "$210.00"
                ],
                "sku": "Item 1377159"
            },
            {
                "swatch_group": "Standard size",
                "flag_label": null,
                "size": null,
                "name": [
                    "Size: 1 oz/ 30 mL"
                ],
                "price": [
                    "$120.00"
                ],
                "sku": "Item 1233139"
            },
            {
                "swatch_group": "Mini size",
                "flag_label": null,
                "size": null,
                "name": [
                    "Size: 0.68 oz/ 20 mL"
                ],
                "price": [
                    "$75.00"
                ],
                "sku": "Item 1233121"
            },
            {
                "swatch_group": "Mini size",
                "flag_label": null,
                "size": null,
                "name": [
                    "Size: 0.33oz/10mL"
                ],
                "price": [
                    "$43.00"
                ],
                "sku": "Item 2175743"
            }
        ],
        "rating": "width:91.672%",
        "product_reviews": "5.1K",
        "ingredients": "Alcohol, Parfum/Fragrance, Aqua/Water, Benzyl Salicylate, Linalool, Butyl Methoxydibenzoylmethane, Ethylhexyl Methoxycinnamate, Limonene, Pentaerythrityl Tetra-Di-T-Butyl Hydroxyhydrocinnamate, Coumarin, Benzyl Alcohol, Benzyl Benzoate, Citral, Ci 19140/Yellow 5, Ci 60730/Ext. Violet 2, Ci 17200/Red 33.",
        "n_loves": "242.7K",
        "categories": [
            "Fragrance",
            "Women",
            "Perfume"
        ]
    },
    {
        "url": "https://www.sephora.com/ca/en/product/spicebomb-eau-de-tiolette-gift-set-P506126",
        "error": "",
        "scrape_timestamp": "08/22/2023, 21:21:31",
        "product_name": "Spicebomb Eau de Tiolette Gift Set",
        "brand_name": "Viktor&Rolf",
        "options": [],
        "rating": "",
        "product_reviews": "",
        "ingredients": "Alcohol, Parfum/Fragrance, Aqua/Water, Limonene, Coumarin, Butyl Methoxydibenzoylmethane, Linalool, Ethylhexyl Salicylate, Eugenol, Citronellol, Methyl Anthranilate, Citral, Geraniol, Ci 60730/Ext. Violet 2, Ci 14700/Red 4.",
        "n_loves": "187",
        "categories": [
            "Fragrance",
            "Value & Gift Sets",
            "Cologne Gift Sets"
        ]
    },
    {
        "url": "https://www.sephora.com/ca/en/product/mini-good-fortune-flowerbomb-perfume-set-P503641",
        "error": "Product not available",
        "scrape_timestamp": "08/22/2023, 21:21:41"
    },
    {
        "url": "https://www.sephora.com/ca/en/product/viktor-rolf-flowerbomb-ruby-orchid-eau-de-parfum-P479358",
        "error": "",
        "scrape_timestamp": "08/22/2023, 21:21:50",
        "product_name": "Flowerbomb Ruby Orchid Eau de Parfum",
        "brand_name": "Viktor&Rolf",
        "options": [
            {
                "swatch_group": "Standard size",
                "flag_label": "ONLY A FEW LEFT",
                "size": null,
                "name": [
                    "Size: 1.7 oz/ 50 mL",
                    "ONLY A FEW LEFT"
                ],
                "price": [
                    "$163.00"
                ],
                "sku": "Item 2480572"
            },
            {
                "swatch_group": "Mini size",
                "flag_label": null,
                "size": null,
                "name": [
                    "Size: 0.34 oz/ 10 mL"
                ],
                "price": [
                    "$43.00"
                ],
                "sku": "Item 2480598"
            }
        ],
        "rating": "width:90.108%",
        "product_reviews": "558",
        "ingredients": "Alcohol, Parfum/Fragrance, Aqua/Water/Eau, Linalool, Benzyl Salicylate, Benzyl Alcohol, Butyl Methoxydibenzoylmethane, Hydroxycitronellal, Limonene, Coumarin, Methyl Anthranilate, Isoeugenol, Benzyl Benzoate, Citronellol, Citral, C1 17200/Red 33, Ci 60730/Ext. Violet 2.",
        "n_loves": "39.7K",
        "categories": [
            "Fragrance",
            "Women",
            "Perfume"
        ]
    },
    {
        "url": "https://www.sephora.com/ca/en/product/flowerbomb-bath-body-collection-P371607",
        "error": "",
        "scrape_timestamp": "08/22/2023, 21:22:04",
        "product_name": "Flowerbomb Body Lotion",
        "brand_name": "Viktor&Rolf",
        "options": [
            {
                "swatch_group": "Standard size",
                "flag_label": "ONLY A FEW LEFT",
                "size": "Size 6.7 oz/ 200 mL",
                "name": [
                    "ONLY A FEW LEFT"
                ],
                "price": [
                    "$73.00"
                ],
                "sku": "Item 1233162"
            }
        ],
        "rating": "width:88.33399999999999%",
        "product_reviews": "36",
        "ingredients": "Unknown Ingredients",
        "n_loves": "7.4K",
        "categories": [
            "Bath & Body",
            "Body Moisturizers",
            "Body Lotions & Body Oils"
        ]
    },
    {
        "url": "https://www.sephora.com/ca/en/product/spicebomb-infrared-eau-de-parfum-P505914",
        "error": "",
        "scrape_timestamp": "08/22/2023, 21:22:17",
        "product_name": "Spicebomb Infrared Eau de Parfum",
        "brand_name": "Viktor&Rolf",
        "options": [
            {
                "swatch_group": "Standard size",
                "flag_label": "NEW",
                "size": null,
                "name": [
                    "Size: 1.7 oz / 50 mL eau de parfum spray",
                    "NEW"
                ],
                "price": [
                    "$120.00"
                ],
                "sku": "Item 2704153"
            },
            {
                "swatch_group": "Standard size",
                "flag_label": "NEW",
                "size": null,
                "name": [
                    "Size: 3 oz / 90 mL eau de parfum spray",
                    "NEW",
                    "ONLY A FEW LEFT"
                ],
                "price": [
                    "$175.00"
                ],
                "sku": "Item 2651909"
            }
        ],
        "rating": "width:89.95%",
        "product_reviews": "201",
        "ingredients": "Alcohol, Parfum / Fragrance, Aqua / Water / Eau, Limonene, Linalool, Coumarin, Eugenol, Cinnamyl Alcohol, Geraniol, Cinnamal, Citral, Benzyl Benzoate, Citronellol.",
        "n_loves": "542",
        "categories": [
            "Fragrance",
            "Men",
            "Cologne"
        ]
    },
    {
        "url": "https://www.sephora.com/ca/en/product/spicebomb-night-vision-P445721",
        "error": "",
        "scrape_timestamp": "08/22/2023, 21:22:33",
        "product_name": "Spicebomb Night Vision",
        "brand_name": "Viktor&Rolf",
        "options": [
            {
                "swatch_group": "Standard size",
                "flag_label": "ONLY A FEW LEFT",
                "size": null,
                "name": [
                    "Size: 1.7 oz/ 50 mL",
                    "ONLY A FEW LEFT"
                ],
                "price": [
                    "$132.00"
                ],
                "sku": "Item 2230944"
            },
            {
                "swatch_group": "Standard size",
                "flag_label": "ONLY A FEW LEFT",
                "size": null,
                "name": [
                    "Size: 3.04 oz/ 90mL",
                    "ONLY A FEW LEFT"
                ],
                "price": [
                    "$163.00"
                ],
                "sku": "Item 2230951"
            }
        ],
        "rating": "width:87.682%",
        "product_reviews": "138",
        "ingredients": "Alcohol, Parfum/Fragrance, Aqua/Water, Benzyl Salicylate, Linalool, Limonene, Benzyl Alcohol, Butyl Methoxydibenzoylmethane, Coumarin, Citronellol, Hydroxycitronellal, Alpha-Isomethyl Ionone, Citral, Eugenol, Geraniol, Benzyl Benzoate, Tris (Tetramethylhydroxypiperidinol) Citrate, Cinnamal.",
        "n_loves": "6.3K",
        "categories": [
            "Fragrance",
            "Men",
            "Cologne"
        ]
    },
    {
        "url": "https://www.sephora.com/ca/en/product/flowerbomb-eau-de-parfum-perfume-gift-set-P504326",
        "error": "",
        "scrape_timestamp": "08/22/2023, 21:22:55",
        "product_name": "Flowerbomb Eau de Parfum Perfume Gift Set",
        "brand_name": "Viktor&Rolf",
        "options": [],
        "rating": "width:95.55999999999999%",
        "product_reviews": "410",
        "ingredients": "Alcohol, Parfum/Fragrance, Aqua/Water, Benzyl Salicylate, Linalool, Butyl Methoxydibenzoylmethane, Ethylhexyl Methoxycinnamate, Limonene, Pentaerythrityl Tetra-Di-T-Butyl Hydroxyhydrocinnamate, Coumarin, Benzyl Alcohol, Benzyl Benzoate, Citral, CI 19140/Yellow 5, CI 60730/Ext. Violet 2, CI 17200/Red 33.",
        "n_loves": "5.4K",
        "categories": [
            "Fragrance",
            "Value & Gift Sets",
            "Perfume Gift Sets"
        ]
    },
    {
        "url": "https://www.sephora.com/ca/en/product/flowerbomb-travel-spray-P446119",
        "error": "",
        "scrape_timestamp": "08/22/2023, 21:23:06",
        "product_name": "Flowerbomb Travel Spray",
        "brand_name": "Viktor&Rolf",
        "options": [
            {
                "swatch_group": "Mini size",
                "flag_label": null,
                "size": null,
                "name": [
                    "Size: 0.33oz/10mL"
                ],
                "price": [
                    "$43.00"
                ],
                "sku": "Item 2175743"
            }
        ],
        "rating": "width:91.726%",
        "product_reviews": "5K",
        "ingredients": "Alcohol, Parfum/Fragrance, Aqua/Water, Benzyl Salicylate, Linalool, Butyl Methoxydibenzoylmethane, Ethylhexyl Methoxycinnamate, Limonene, Pentaerythrityl Tetra-Di-T-Butyl Hydroxyhydrocinnamate, Coumarin, Benzyl Alcohol, Benzyl Benzoate, Citral, Ci 19140/Yellow 5, Ci 60730/Ext. Violet 2, Ci 17200/Red 33.",
        "n_loves": "48.4K",
        "categories": [
            "Fragrance",
            "Women",
            "Rollerballs & Travel Size"
        ]
    },
    {
        "url": "https://www.sephora.com/ca/en/product/spicebomb-P376737",
        "error": "",
        "scrape_timestamp": "08/22/2023, 21:23:18",
        "product_name": "Spicebomb",
        "brand_name": "Viktor&Rolf",
        "options": [
            {
                "swatch_group": "Standard size",
                "flag_label": "OUT OF STOCK",
                "size": null,
                "name": [
                    "Size: 1.7 oz/ 50 mL",
                    "OUT OF STOCK"
                ],
                "price": [
                    "$136.00"
                ],
                "sku": "Item 1463199"
            },
            {
                "swatch_group": "Standard size",
                "flag_label": "ONLY A FEW LEFT",
                "size": null,
                "name": [
                    "Size: 3.04 oz/ 90 mL",
                    "ONLY A FEW LEFT"
                ],
                "price": [
                    "$163.00"
                ],
                "sku": "Item 1463207"
            }
        ],
        "rating": "width:93.76400000000001%",
        "product_reviews": "526",
        "ingredients": "Parfum / Fragrance,\nAqua / Water,\nLimonene,\nCoumarin,\nEthylhexyl Methoxycinnamate,\nLinalool,\nButyl Methoxydibenzoylmethane,\nEthylhexyl Salicylate,\nEugenol,\nCitronellol,\nPentaerythrityl Tetra-Di-T-Butyl Hydroxyhydrocinnamate,\nMethyl Anthranilate,\nCitral,\nGeraniol,\nCi 60730 / Ext. Violet 2,\nCi 14700 / Red 4.",
        "n_loves": "23.8K",
        "categories": [
            "Fragrance",
            "Men",
            "Cologne"
        ]
    },
    {
        "url": "https://www.sephora.com/ca/en/product/viktor-rolf-good-fortune-eau-de-parfum-P484086",
        "error": "",
        "scrape_timestamp": "08/22/2023, 21:23:41",
        "product_name": "Good Fortune Eau de Parfum",
        "brand_name": "Viktor&Rolf",
        "options": [
            {
                "swatch_group": "Standard size",
                "flag_label": null,
                "size": null,
                "name": [
                    "Size: 3 oz / 90 mL"
                ],
                "price": [
                    "$210.00"
                ],
                "sku": "Item 2553329"
            },
            {
                "swatch_group": "Standard size",
                "flag_label": "ONLY A FEW LEFT",
                "size": null,
                "name": [
                    "Size: 1.7 oz / 50 mL eau de parfum spray",
                    "ONLY A FEW LEFT"
                ],
                "price": [
                    "$163.00"
                ],
                "sku": "Item 2553311"
            },
            {
                "swatch_group": "Standard size",
                "flag_label": null,
                "size": null,
                "name": [
                    "Size: 1 oz / 30 mL"
                ],
                "price": [
                    "$120.00"
                ],
                "sku": "Item 2553337"
            },
            {
                "swatch_group": "Mini size",
                "flag_label": null,
                "size": null,
                "name": [
                    "Size: 0.3 oz / 10 mL"
                ],
                "price": [
                    "$43.00"
                ],
                "sku": "Item 2553303"
            },
            {
                "swatch_group": "Refill size",
                "flag_label": null,
                "size": null,
                "name": [
                    "Size: 3.4 oz / 100 mL eau de parfum spray"
                ],
                "price": [
                    "$160.00"
                ],
                "sku": "Item 2558658"
            }
        ],
        "rating": "width:87.94800000000001%",
        "product_reviews": "1.5K",
        "ingredients": "Alcohol, Parfum / Fragrance, Aqua/Water/Eau, Dipropylene Glycol, Limonene, Linalool, Benzyl Salicylate, Benzyl Alcohol, Butyl Methoxydibenzoylmethane, Hydroxicitronellal, Methyl Anthranilate, Citronellol, Alpha-Isomethyl Ionone, Coumarin, Geraniol, Isoeugenol, Benzyl Benzoate, Citral, Trie(Tetramethylhydroxypiperidinol) Citrate, Eugenol, Farnesol, Ci 60730 / Ext. Violet 2, Ci 17200 / Red 33.",
        "n_loves": "17.1K",
        "categories": [
            "Fragrance",
            "Women",
            "Perfume"
        ]
    },
    {
        "url": "https://www.sephora.com/ca/en/product/good-fortune-eau-de-parfum-perfume-set-P504295",
        "error": "",
        "scrape_timestamp": "08/22/2023, 21:24:10",
        "product_name": "Good Fortune Eau de Parfum Perfume Set",
        "brand_name": "Viktor&Rolf",
        "options": [],
        "rating": "",
        "product_reviews": "",
        "ingredients": "Alcohol, Parfum/Fragrance, Aqua/Water/Eau, Dipropylene Glycol, Limonene, Linalool, Benzyl Salicylate, Benzyl Alcohol, Butyl Methoxydibenzoylmethane, Hydroxicitronellal, Methyl Anthranilate, Citronellol, Alpha-Isomethyl Ionone, Coumarin, Geraniol, Isoeugenol, Benzyl Benzoate, Citral, Trie (Tetramethylhydroxypiperidinol) Citrate, Eugenol, Farnesol, Ci 60730/Ext. Violet 2, CI 17200/Red 33.",
        "n_loves": "186",
        "categories": [
            "Fragrance",
            "Value & Gift Sets",
            "Perfume Gift Sets"
        ]
    },
    {
        "url": "https://www.sephora.com/ca/en/product/viktor-rolf-good-fortune-eau-de-parfum-travel-spray-P484087",
        "error": "",
        "scrape_timestamp": "08/22/2023, 21:24:20",
        "product_name": "Good Fortune Eau de Parfum Travel Spray",
        "brand_name": "Viktor&Rolf",
        "options": [
            {
                "swatch_group": "Mini size",
                "flag_label": null,
                "size": null,
                "name": [
                    "Size: 0.3 oz / 10 mL"
                ],
                "price": [
                    "$43.00"
                ],
                "sku": "Item 2553303"
            }
        ],
        "rating": "width:87.94800000000001%",
        "product_reviews": "1.5K",
        "ingredients": "Alcohol, Parfum / Fragrance, Aqua/Water/Eau, Dipropylene Glycol, Limonene, Linalool, Benzyl Salicylate, Benzyl Alcohol, Butyl Methoxydibenzoylmethane, Hydroxicitronellal, Methyl Anthranilate, Citronellol, Alpha-Isomethyl Ionone, Coumarin, Geraniol, Isoeugenol, Benzyl Benzoate, Citral, Trie(Tetramethylhydroxypiperidinol) Citrate, Eugenol, Farnesol, Ci 60730 / Ext. Violet 2, Ci 17200 / Red 33.",
        "n_loves": "14.2K",
        "categories": [
            "Fragrance",
            "Women",
            "Rollerballs & Travel Size"
        ]
    },
    {
        "url": "https://www.sephora.com/ca/en/product/spicebomb-night-vision-eau-de-parfum-P461989",
        "error": "",
        "scrape_timestamp": "08/22/2023, 21:24:32",
        "product_name": "Spicebomb Night Vision Eau de Parfum",
        "brand_name": "Viktor&Rolf",
        "options": [
            {
                "swatch_group": "Standard size",
                "flag_label": "ONLY A FEW LEFT",
                "size": null,
                "name": [
                    "Size: 3 oz/ 90 mL",
                    "ONLY A FEW LEFT"
                ],
                "price": [
                    "$176.00"
                ],
                "sku": "Item 2373520"
            }
        ],
        "rating": "width:90.534%",
        "product_reviews": "131",
        "ingredients": "Alcohol, Parfum / Fragrance, Aqua / Water, Benzyl Salicylate, Linalool, Limonene, Benzyl Alcohol, Ethylhexyl Salicylate, Butyl Methoxydibenzoylmethane, Coumarin, Citronellol, Hydroxycitronellal, Benzyl Benzoate, Alpha-Isomethyl Ionone, Benzyl Cinnamate, Citral, Eugenol, Geraniol, Cinnamal.",
        "n_loves": "3.6K",
        "categories": [
            "Fragrance",
            "Men",
            "Cologne"
        ]
    }
]